{
  "11610117": "Married Scholars",
  "146102025": "Married Scholars",
  "146103022": "Married Scholars",
  "10610404": "Married Scholars",
  "136103037": "Married Scholars",
  "136103006": "Married Scholars",
  "126104027": "Married Scholars",
  "156101006": "Married Scholars",
  "126106004": "Married Scholars",
  "126101005": "Married Scholars",
  "146103004": "Married Scholars",
  "146103002": "Married Scholars",
  "116122033": "Married Scholars",
  "11610233": "Married Scholars",
  "136103034": "Married Scholars",
  "166122013": "Married Scholars",
  "146107019": "Married Scholars",
  "11610227": "Married Scholars",
  "126107014": "Married Scholars",
  "136103029": "Married Scholars",
  "126107029": "Married Scholars",
  "136107003": "Married Scholars",
  "126104022": "Married Scholars",
  "126102018": "Married Scholars",
  "156104013": "Married Scholars",
  "156102023": "Married Scholars",
  "166101001": "Married Scholars",
  "157107001": "Married Scholars",
  "146102016": "Married Scholars",
  "10610224": "Married Scholars",
  "166141003": "Married Scholars",
  "136102003": "Married Scholars",
  "166151001": "Married Scholars",
  "166105007": "Married Scholars",
  "16612203": "Married Scholars",
  "157106002": "Married Scholars",
  "146104037": "Married Scholars",
  "166121020": "Married Scholars",
  "164103114": "Married Scholars",
  "126102029": "Married Scholars",
  "146121017": "Married Scholars",
  "126151004": "Married Scholars",
  "146104008": "Married Scholars",
  "156107032": "Married Scholars",
  "11612122": "Married Scholars",
  "10610211": "Married Scholars",
  "146107023": "Married Scholars",
  "126141003": "Married Scholars",
  "136102004": "Married Scholars",
  "146141015": "Married Scholars",
  "136122027": "Married Scholars",
  "136103030": "Married Scholars",
  "146103012": "Married Scholars",
  "10610320": "Married Scholars",
  "136105006": "Married Scholars",
  "126103011": "Married Scholars",
  "136121015": "Married Scholars",
  "156141007": "Married Scholars",
  "7610605": "Married Scholars",
  "11610409": "Married Scholars",
  "136103017": "Married Scholars",
  "136201001": "Married Scholars",
  "11612124": "Married Scholars",
  "146107022": "Married Scholars",
  "146102012": "Married Scholars",
  "146123009": "Married Scholars",
  "11612109": "Married Scholars",
  "146106040": "Married Scholars",
  "136107008": "Married Scholars",
  "126105001": "Married Scholars",
  "146106041": "Married Scholars",
  "146103024": "Married Scholars",
  "126121027": "Married Scholars",
  "146103001": "Married Scholars",
  "126104032": "Married Scholars",
  "146103028": "Married Scholars",
  "164102071": "Married Scholars",
  "146107018": "Married Scholars",
  "156102025": "Married Scholars",
  "164102073": "Married Scholars",
  "136103041": "Married Scholars",
  "146105011": "Married Scholars",
  "166104038": "Married Scholars",
  "156153002": "Married Scholars",
  "146141016": "Married Scholars",
  "126106032": "Married Scholars",
  "166155002": "Married Scholars",
  "11610319": "Married Scholars",
  "156103010": "Married Scholars",
  "136151001": "Married Scholars",
  "126103023": "Married Scholars",
  "166101009": "Married Scholars",
  "10610415": "Married Scholars",
  "136103008": "Married Scholars",
  "146101017": "Married Scholars",
  "126121019": "Married Scholars",
  "11614103": "Married Scholars",
  "11610113": "Married Scholars",
  "11610716": "Married Scholars",
  "126102023": "Married Scholars",
  "166104028": "Married Scholars",
  "146107040": "Married Scholars",
  "136107006": "Married Scholars",
  "156101004": "Married Scholars",
  "11614107": "Married Scholars",
  "156107039": "Married Scholars",
  "126122002": "Married Scholars",
  "146104004": "Married Scholars",
  "156101010": "Married Scholars",
  "156107029": "Married Scholars",
  "136103010": "Married Scholars",
  "126103007": "Married Scholars",
  "136102027": "Married Scholars",
  "126107038": "Married Scholars",
  "146104031": "Married Scholars",
  "1461010001": "Married Scholars",
  "146102013": "Married Scholars",
  "166107117": "Married Scholars",
  "156105008": "Married Scholars",
  "156122052": "Married Scholars",
  "126201002": "Married Scholars",
  "146105005": "Married Scholars",
  "146103021": "Married Scholars",
  "136104011": "Married Scholars",
  "11610333": "Married Scholars",
  "136103004": "Married Scholars",
  "156102033": "Married Scholars",
  "146104010": "Married Scholars",
  "166121021": "Married Scholars",
  "11610303": "Married Scholars",
  "11610225": "Married Scholars",
  "11610203": "Married Scholars",
  "146106038": "Married Scholars",
  "136121005": "Married Scholars",
  "126106038": "Married Scholars",
  "166105009": "Married Scholars",
  "166104024": "Married Scholars",
  "126102001": "Married Scholars",
  "156141006": "Married Scholars",
  "136101002": "Married Scholars",
  "156102003": "Married Scholars",
  "126121015": "Married Scholars",
  "136122034": "Married Scholars",
  "126102025": "Married Scholars",
  "126106006": "Married Scholars",
  "156104029": "Married Scholars",
  "146151011": "Married Scholars",
  "156107014": "Married Scholars",
  "136103025": "Married Scholars",
  "146121014": "Married Scholars",
  "166152105": "Married Scholars",
  "156104045": "Married Scholars",
  "126122025": "Married Scholars",
  "156105020": "Married Scholars",
  "126107030": "Married Scholars",
  "156102029": "Married Scholars",
  "136121003": "Married Scholars",
  "166154002": "Married Scholars",
  "164102072": "Married Scholars",
  "146106025": "Married Scholars",
  "166101007": "Married Scholars",
  "154103113": "Married Scholars",
  "126102004": "Married Scholars",
  "136104007": "Married Scholars",
  "146101016": "Married Scholars"
}